{
  "_id": "54621c465b791cf008906ed6",
  "year": 1870,
  "races": 5,
  "anniversary": 4,
  "__v": 0,
  "results": [
    {
      "_id": "54621c4f5b791cf008906ed7",
      "year": "54621c465b791cf008906ed6",
      "boat": "546218f79722c45a057d9ffe",
      "race": 0,
      "position": 1,
      "__v": 0
    },
    {
      "_id": "54621c505b791cf008906ed8",
      "year": "54621c465b791cf008906ed6",
      "boat": "546218f79722c45a057d9ffe",
      "race": 1,
      "position": 0,
      "__v": 0
    },
    {
      "_id": "54621c515b791cf008906ed9",
      "year": "54621c465b791cf008906ed6",
      "boat": "546218f79722c45a057d9ffe",
      "race": 2,
      "position": 0,
      "__v": 0
    },
    {
      "_id": "54621c515b791cf008906eda",
      "year": "54621c465b791cf008906ed6",
      "boat": "546218f79722c45a057d9ffe",
      "race": 3,
      "position": 0,
      "__v": 0
    },
    {
      "_id": "54621c525b791cf008906edb",
      "year": "54621c465b791cf008906ed6",
      "boat": "546218f79722c45a057d9ffe",
      "race": 4,
      "position": 0,
      "__v": 0
    },
    {
      "_id": "54621c525b791cf008906edc",
      "year": "54621c465b791cf008906ed6",
      "boat": "546218f79722c45a057d9ffe",
      "race": 5,
      "position": 0,
      "__v": 0
    },
    {
      "_id": "54621c545b791cf008906edd",
      "year": "54621c465b791cf008906ed6",
      "boat": "546218249722c45a057d9ff9",
      "race": 0,
      "position": 0,
      "__v": 0
    },
    {
      "_id": "54621c555b791cf008906ede",
      "year": "54621c465b791cf008906ed6",
      "boat": "546218249722c45a057d9ff9",
      "race": 1,
      "position": 1,
      "__v": 0
    },
    {
      "_id": "54621c565b791cf008906edf",
      "year": "54621c465b791cf008906ed6",
      "boat": "546218249722c45a057d9ff9",
      "race": 2,
      "position": 1,
      "__v": 0
    },
    {
      "_id": "54621c565b791cf008906ee0",
      "year": "54621c465b791cf008906ed6",
      "boat": "546218249722c45a057d9ff9",
      "race": 3,
      "position": 1,
      "__v": 0
    },
    {
      "_id": "54621c575b791cf008906ee1",
      "year": "54621c465b791cf008906ed6",
      "boat": "546218249722c45a057d9ff9",
      "race": 4,
      "position": 1,
      "__v": 0
    },
    {
      "_id": "54621c575b791cf008906ee2",
      "year": "54621c465b791cf008906ed6",
      "boat": "546218249722c45a057d9ff9",
      "race": 5,
      "position": 1,
      "__v": 0
    },
    {
      "_id": "54621c5a5b791cf008906ee3",
      "year": "54621c465b791cf008906ed6",
      "boat": "5462190a9722c45a057da001",
      "race": 0,
      "position": 2,
      "__v": 0
    },
    {
      "_id": "54621c5b5b791cf008906ee4",
      "year": "54621c465b791cf008906ed6",
      "boat": "5462190a9722c45a057da001",
      "race": 1,
      "position": 2,
      "__v": 0
    },
    {
      "_id": "54621c5b5b791cf008906ee5",
      "year": "54621c465b791cf008906ed6",
      "boat": "5462190a9722c45a057da001",
      "race": 2,
      "position": 2,
      "__v": 0
    },
    {
      "_id": "54621c5c5b791cf008906ee6",
      "year": "54621c465b791cf008906ed6",
      "boat": "5462190a9722c45a057da001",
      "race": 3,
      "position": 3,
      "__v": 0
    },
    {
      "_id": "54621c5d5b791cf008906ee7",
      "year": "54621c465b791cf008906ed6",
      "boat": "5462190a9722c45a057da001",
      "race": 4,
      "position": 3,
      "__v": 0
    },
    {
      "_id": "54621c5d5b791cf008906ee8",
      "year": "54621c465b791cf008906ed6",
      "boat": "5462190a9722c45a057da001",
      "race": 5,
      "position": 3,
      "__v": 0
    },
    {
      "_id": "54621c625b791cf008906ee9",
      "year": "54621c465b791cf008906ed6",
      "boat": "546218869722c45a057d9ffc",
      "race": 1,
      "position": 3,
      "__v": 0
    },
    {
      "_id": "54621c625b791cf008906eea",
      "year": "54621c465b791cf008906ed6",
      "boat": "546218869722c45a057d9ffc",
      "race": 0,
      "position": 3,
      "__v": 0
    },
    {
      "_id": "54621c665b791cf008906eeb",
      "year": "54621c465b791cf008906ed6",
      "boat": "546218869722c45a057d9ffc",
      "race": 2,
      "position": 4,
      "__v": 0
    },
    {
      "_id": "54621c675b791cf008906eec",
      "year": "54621c465b791cf008906ed6",
      "boat": "546218869722c45a057d9ffc",
      "race": 3,
      "position": 5,
      "__v": 0
    },
    {
      "_id": "54621c685b791cf008906eed",
      "year": "54621c465b791cf008906ed6",
      "boat": "546218869722c45a057d9ffc",
      "race": 4,
      "position": 6,
      "__v": 0
    },
    {
      "_id": "54621c695b791cf008906eee",
      "year": "54621c465b791cf008906ed6",
      "boat": "546218869722c45a057d9ffc",
      "race": 5,
      "position": 6,
      "__v": 0
    },
    {
      "_id": "54621c6c5b791cf008906ef0",
      "year": "54621c465b791cf008906ed6",
      "boat": "546218f79722c45a057d9fff",
      "race": 1,
      "position": 4,
      "__v": 0
    },
    {
      "_id": "54621c6c5b791cf008906ef1",
      "year": "54621c465b791cf008906ed6",
      "boat": "546218f79722c45a057d9fff",
      "race": 2,
      "position": 3,
      "__v": 0
    },
    {
      "_id": "54621c6d5b791cf008906ef2",
      "year": "54621c465b791cf008906ed6",
      "boat": "546218f79722c45a057d9fff",
      "race": 3,
      "position": 2,
      "__v": 0
    },
    {
      "_id": "54621c6e5b791cf008906ef3",
      "year": "54621c465b791cf008906ed6",
      "boat": "546218f79722c45a057d9fff",
      "race": 4,
      "position": 2,
      "__v": 0
    },
    {
      "_id": "54621c6e5b791cf008906ef4",
      "year": "54621c465b791cf008906ed6",
      "boat": "546218f79722c45a057d9fff",
      "race": 5,
      "position": 2,
      "__v": 0
    },
    {
      "_id": "54621cc55b791cf008906ef6",
      "year": "54621c465b791cf008906ed6",
      "boat": "546218f79722c45a057d9fff",
      "race": 0,
      "position": 5,
      "__v": 0
    },
    {
      "_id": "54621cc75b791cf008906ef7",
      "year": "54621c465b791cf008906ed6",
      "boat": "54621a555b791cf008906e29",
      "race": 0,
      "position": 4,
      "__v": 0
    },
    {
      "_id": "54621cc85b791cf008906ef8",
      "year": "54621c465b791cf008906ed6",
      "boat": "54621a555b791cf008906e29",
      "race": 1,
      "position": 5,
      "__v": 0
    },
    {
      "_id": "54621cc95b791cf008906ef9",
      "year": "54621c465b791cf008906ed6",
      "boat": "54621a555b791cf008906e29",
      "race": 2,
      "position": 6,
      "__v": 0
    },
    {
      "_id": "54621cc95b791cf008906efa",
      "year": "54621c465b791cf008906ed6",
      "boat": "54621a555b791cf008906e29",
      "race": 3,
      "position": 6,
      "__v": 0
    },
    {
      "_id": "54621ccb5b791cf008906efc",
      "year": "54621c465b791cf008906ed6",
      "boat": "54621a555b791cf008906e29",
      "race": 4,
      "position": 5,
      "__v": 0
    },
    {
      "_id": "54621ccc5b791cf008906efd",
      "year": "54621c465b791cf008906ed6",
      "boat": "54621a555b791cf008906e29",
      "race": 5,
      "position": 5,
      "__v": 0
    },
    {
      "_id": "54621cd45b791cf008906efe",
      "year": "54621c465b791cf008906ed6",
      "boat": "5462182c9722c45a057d9ffa",
      "race": 0,
      "position": 6,
      "__v": 0
    },
    {
      "_id": "54621cd45b791cf008906eff",
      "year": "54621c465b791cf008906ed6",
      "boat": "5462182c9722c45a057d9ffa",
      "race": 1,
      "position": 6,
      "__v": 0
    },
    {
      "_id": "54621cd55b791cf008906f00",
      "year": "54621c465b791cf008906ed6",
      "boat": "5462182c9722c45a057d9ffa",
      "race": 2,
      "position": 5,
      "__v": 0
    },
    {
      "_id": "54621cd65b791cf008906f01",
      "year": "54621c465b791cf008906ed6",
      "boat": "5462182c9722c45a057d9ffa",
      "race": 3,
      "position": 4,
      "__v": 0
    },
    {
      "_id": "54621cd65b791cf008906f02",
      "year": "54621c465b791cf008906ed6",
      "boat": "5462182c9722c45a057d9ffa",
      "race": 4,
      "position": 4,
      "__v": 0
    },
    {
      "_id": "54621cd75b791cf008906f03",
      "year": "54621c465b791cf008906ed6",
      "boat": "5462182c9722c45a057d9ffa",
      "race": 5,
      "position": 4,
      "__v": 0
    }
  ],
  "divisions": [
    7
  ]
}